jutge/__init__.py
jutge/check_repo.py
jutge/grade_repo.py
jutge/process.py
jutge/status.py
jutge/utils.py
jutge/judges/__init__.py
jutge/judges/base_judge.py
jutge/judges/java_judge.py
jutge/judges/mongodb_judge.py
jutge/judges/sql_judge.py
jutge/models/__init__.py
jutge/models/exercise.py
jutge/models/unit_test.py
jutge_joapuiib-1.0.9.dist-info/METADATA
jutge_joapuiib-1.0.9.dist-info/WHEEL
jutge_joapuiib-1.0.9.dist-info/entry_points.txt
jutge_joapuiib-1.0.9.dist-info/top_level.txt
jutge_joapuiib-1.0.9.dist-info/RECORD
