Metadata-Version: 2.1
Name: jutge-joapuiib
Version: 1.0.9
Summary: CLI Judge to validate SQL and Java exercises
Home-page: https://github.com/joapuiib/jutge
Author: joapuiib
Author-email: joapuiib@gmail.com
Project-URL: Source, https://github.com/joapuiib/jutge/
Project-URL: Issues, https://github.com/joapuiib/jutge/issues
Classifier: Programming Language :: Python :: 3.8
Classifier: License :: OSI Approved :: GNU General Public License v3 (GPLv3)
Requires-Python: >=3.8
Requires-Dist: ansiwrap >=0.8.4
Requires-Dist: pygments >=2.11.2
Requires-Dist: GitPython >=3.1.26
Requires-Dist: pyperclip >=1.8.2
Requires-Dist: colorama >=0.4.4
